LICENSE
MANIFEST.in
README.rst
setup.py
aino_convert.egg-info/PKG-INFO
aino_convert.egg-info/SOURCES.txt
aino_convert.egg-info/dependency_links.txt
aino_convert.egg-info/top_level.txt
convert/__init__.py
convert/base.py
convert/fields.py
convert/helpers.py
convert/metadata.py
convert/widgets.py
convert/conf/__init__.py
convert/conf/defaults.py
convert/templatetags/__init__.py
convert/templatetags/convert_tags.py
docs/index.rst
docs/installation.rst