Metadata-Version: 1.0
Name: aino-convert
Version: 0.1.0.9
Summary: Magick for Django
Home-page: http://bitbucket.org/aino/aino-convert/
Author: Mikko Hellsing
Author-email: mikko@aino.se
License: BSD
Platform: any
Classifier: Development Status :: 3 - Alpha
Classifier: Environment :: Web Environment
Classifier: Intended Audience :: Developers
Classifier: License :: OSI Approved :: BSD License
Classifier: Operating System :: OS Independent
Classifier: Programming Language :: Python
Classifier: Topic :: Internet :: WWW/HTTP :: Dynamic Content
Classifier: Topic :: Multimedia :: Graphics
Classifier: Framework :: Django
